dimos/__init__.py
dimos-0.0.0.dist-info/METADATA
dimos-0.0.0.dist-info/WHEEL
dimos-0.0.0.dist-info/top_level.txt
dimos-0.0.0.dist-info/RECORD
